{
    "name": "ray.data.read_api.from_mars",
    "signature": "ray.data.read_api.from_mars(df: 'mars.dataframe.DataFrame') -> ray.data.dataset.MaterializedDataset",
    "summary": "Create a :class:`~ray.data.Dataset` from a",
    "desc": "`Mars DataFrame <https://mars-project.readthedocs.io/en/latest/reference/dataframe/index.html>`_.",
    "args": [
        {
            "name": "df",
            "type": null,
            "desc": "A `Mars DataFrame`_, which must be executed by Mars-on-Ray."
        }
    ],
    "returns": "A :class:`~ray.data.MaterializedDataset` holding rows read from the DataFrame.",
    "examples": []
}